envipy_c_stuff/__init__.py
envipy_c_stuff/meandel.pyd
envipy_c_stuff-0.0.1.dist-info/DESCRIPTION.rst
envipy_c_stuff-0.0.1.dist-info/METADATA
envipy_c_stuff-0.0.1.dist-info/RECORD
envipy_c_stuff-0.0.1.dist-info/WHEEL
envipy_c_stuff-0.0.1.dist-info/metadata.json
envipy_c_stuff-0.0.1.dist-info/top_level.txt
