Metadata-Version: 2.0
Name: envipy-c-stuff
Version: 0.0.1
Summary: binary extensions for envip
Home-page: UNKNOWN
Author: Uwe Schmitt
Author-email: mail@uweschmitt.info
License: BSD
Platform: UNKNOWN
